MANIFEST.in
README.txt
setup.cfg
setup.py
./MANIFEST.in
./README.txt
./setup.cfg
./setup.py
./collective/__init__.py
./collective.browserdetector.egg-info/paster_plugins.txt
./collective/browserdetector/README.txt
./collective/browserdetector/__init__.py
./collective/browserdetector/browser.pt
./collective/browserdetector/browser.py
./collective/browserdetector/configure.zcml
./collective/browserdetector/i18n.py
./collective/browserdetector/interfaces.py
./collective/browserdetector/tests.py
./collective/browserdetector/portlets/__init__.py
./collective/browserdetector/portlets/browserdetector.pt
./collective/browserdetector/portlets/browserdetector.py
./collective/browserdetector/portlets/configure.zcml
./collective/browserdetector/profiles/default/cssregistry.xml.example
./collective/browserdetector/profiles/default/metadata.xml
./collective/browserdetector/profiles/default/portlets.xml
./collective/browserdetector/profiles/default/skins.xml
./collective/browserdetector/skins/collective.browserdetector/Chrome.css.dtml
./collective/browserdetector/skins/collective.browserdetector/Chrome.css.dtml.metadata
./collective/browserdetector/skins/collective.browserdetector/Firefox.css.dtml
./collective/browserdetector/skins/collective.browserdetector/Firefox.css.dtml.metadata
./collective/browserdetector/skins/collective.browserdetector/Firefox1.css.dtml
./collective/browserdetector/skins/collective.browserdetector/Firefox1.css.dtml.metadata
./collective/browserdetector/skins/collective.browserdetector/Firefox2.css.dtml
./collective/browserdetector/skins/collective.browserdetector/Firefox2.css.dtml.metadata
./collective/browserdetector/skins/collective.browserdetector/Firefox3.css.dtml
./collective/browserdetector/skins/collective.browserdetector/Firefox3.css.dtml.metadata
./collective/browserdetector/skins/collective.browserdetector/Gecko.css.dtml
./collective/browserdetector/skins/collective.browserdetector/Gecko.css.dtml.metadata
./collective/browserdetector/skins/collective.browserdetector/Gecko2.css.dtml
collective.browserdetector.egg-info/PKG-INFO
collective.browserdetector.egg-info/SOURCES.txt
collective.browserdetector.egg-info/dependency_links.txt
collective.browserdetector.egg-info/entry_points.txt
collective.browserdetector.egg-info/namespace_packages.txt
collective.browserdetector.egg-info/not-zip-safe
collective.browserdetector.egg-info/paster_plugins.txt
collective.browserdetector.egg-info/requires.txt
collective.browserdetector.egg-info/top_level.txt
