Metadata-Version: 1.0
Name: collective.browserdetector
Version: 1.1.2
Summary: A helper Plone extension which makes easier to include resources specific to several types of browsers or platforms.
Home-page: http://dms4u.cz
Author: Lukas Zdych
Author-email: lukas.zdych@dms4u.cz
License: GPL
Keywords: plone browser detection
Platform: UNKNOWN
Classifier: Framework :: Plone
Classifier: Programming Language :: Python
Classifier: Topic :: Software Development :: Libraries :: Python Modules
